{
  "products": [
    {
      "id": "100",
      "pname": "TV",
      "price": 560000
    },
    {
      "id": "00d5",
      "pname": "Computer",
      "price": "45000"
    },
    {
      "id": "295d",
      "pname": "Pen Drive",
      "price": "1600"
    },
    {
      "id": "788e",
      "pname": "Mobile",
      "price": "98000"
    },
    {
      "id": "bb96",
      "pname": "Mobile",
      "price": "98000"
    },
    {
      "id": "aac8",
      "pname": "Mobile",
      "price": "98000"
    }
  ]
}